Workbook

Sheet 日次入力
A1: 売上管理表｜日次入力
A2: 青い字のセルに入力してください。黒い字は自動で計算されます。6行目は記入例です。上書きして使ってください。
A3: この表の合計 | C3: =SUM($C$5:$C$404) | D3: =SUM($D$5:$D$404) | E3: =IFERROR($C$3/$D$3,"") | F3: ←日付を入れた行だけが足されます
A4: 日付 | B4: 曜日 | C4: 売上 | D4: 来客数 | E4: 客単価 | F4: 時間帯 | G4: 支払方法 | H4: 備考 | I4: 月
A5: 2026/10/01 | B5: =IF($A5="","",TEXT($A5,"aaa")) | C5: 128000 | D5: 42 | E5: =IFERROR($C5/$D5,"") | F5: ランチ | G5: 現金 | H5: 雨。来客少なめ | I5: =IF($A5="","",TEXT($A5,"yyyy/mm"))
B6: =IF($A6="","",TEXT($A6,"aaa")) | E6: =IFERROR($C6/$D6,"") | I6: =IF($A6="","",TEXT($A6,"yyyy/mm"))
B7: =IF($A7="","",TEXT($A7,"aaa")) | E7: =IFERROR($C7/$D7,"") | I7: =IF($A7="","",TEXT($A7,"yyyy/mm"))
B8: =IF($A8="","",TEXT($A8,"aaa")) | E8: =IFERROR($C8/$D8,"") | I8: =IF($A8="","",TEXT($A8,"yyyy/mm"))
B9: =IF($A9="","",TEXT($A9,"aaa")) | E9: =IFERROR($C9/$D9,"") | I9: =IF($A9="","",TEXT($A9,"yyyy/mm"))
B10: =IF($A10="","",TEXT($A10,"aaa")) | E10: =IFERROR($C10/$D10,"") | I10: =IF($A10="","",TEXT($A10,"yyyy/mm"))
B11: =IF($A11="","",TEXT($A11,"aaa")) | E11: =IFERROR($C11/$D11,"") | I11: =IF($A11="","",TEXT($A11,"yyyy/mm"))
B12: =IF($A12="","",TEXT($A12,"aaa")) | E12: =IFERROR($C12/$D12,"") | I12: =IF($A12="","",TEXT($A12,"yyyy/mm"))
B13: =IF($A13="","",TEXT($A13,"aaa")) | E13: =IFERROR($C13/$D13,"") | I13: =IF($A13="","",TEXT($A13,"yyyy/mm"))
B14: =IF($A14="","",TEXT($A14,"aaa")) | E14: =IFERROR($C14/$D14,"") | I14: =IF($A14="","",TEXT($A14,"yyyy/mm"))
B15: =IF($A15="","",TEXT($A15,"aaa")) | E15: =IFERROR($C15/$D15,"") | I15: =IF($A15="","",TEXT($A15,"yyyy/mm"))
B16: =IF($A16="","",TEXT($A16,"aaa")) | E16: =IFERROR($C16/$D16,"") | I16: =IF($A16="","",TEXT($A16,"yyyy/mm"))
B17: =IF($A17="","",TEXT($A17,"aaa")) | E17: =IFERROR($C17/$D17,"") | I17: =IF($A17="","",TEXT($A17,"yyyy/mm"))
... B404: =IF($A404="","",TEXT($A404,"aaa")) | E404: =IFERROR($C404/$D404,"") | I404: =IF($A404="","",TEXT($A404,"yyyy/mm"))
A406: ※ 客単価は 売上 ÷ 来客数。来客数が空のときは何も出ません。
A407: ※ この表は400行（13か月ぶん）まで数式が入っています。足りなくなったら最終行をコピーして貼り足してください。

Sheet 月次集計
A1: 売上管理表｜月次集計
A2: 青い字のセルに入力してください。ほかは日次入力シートから自動で集計されます。
A4: 集計を始める月 | B4: 2026/10/01 | C4: ←ここを変えると下の24か月がまとめて動きます
A6: 月 | B6: 売上合計 | C6: 来客数合計 | D6: 客単価平均 | E6: 前月比 | F6: 前年同月比 | G6: 目標 | H6: 達成率
A7: =TEXT(EDATE($B$4,0),"yyyy/mm") | B7: =SUMIF(日次入力!$I$5:$I$404,$A7,日次入力!$C$5:$C$404) | C7: =SUMIF(日次入力!$I$5:$I$404,$A7,日次入力!$D$5:$D$404) | D7: =IFERROR($B7/$C7,"") | H7: =IFERROR($B7/$G7,"")
A8: =TEXT(EDATE($B$4,1),"yyyy/mm") | B8: =SUMIF(日次入力!$I$5:$I$404,$A8,日次入力!$C$5:$C$404) | C8: =SUMIF(日次入力!$I$5:$I$404,$A8,日次入力!$D$5:$D$404) | D8: =IFERROR($B8/$C8,"") | E8: =IFERROR($B8/$B7-1,"") | H8: =IFERROR($B8/$G8,"")
A9: =TEXT(EDATE($B$4,2),"yyyy/mm") | B9: =SUMIF(日次入力!$I$5:$I$404,$A9,日次入力!$C$5:$C$404) | C9: =SUMIF(日次入力!$I$5:$I$404,$A9,日次入力!$D$5:$D$404) | D9: =IFERROR($B9/$C9,"") | E9: =IFERROR($B9/$B8-1,"") | H9: =IFERROR($B9/$G9,"")
A10: =TEXT(EDATE($B$4,3),"yyyy/mm") | B10: =SUMIF(日次入力!$I$5:$I$404,$A10,日次入力!$C$5:$C$404) | C10: =SUMIF(日次入力!$I$5:$I$404,$A10,日次入力!$D$5:$D$404) | D10: =IFERROR($B10/$C10,"") | E10: =IFERROR($B10/$B9-1,"") | H10: =IFERROR($B10/$G10,"")
A11: =TEXT(EDATE($B$4,4),"yyyy/mm") | B11: =SUMIF(日次入力!$I$5:$I$404,$A11,日次入力!$C$5:$C$404) | C11: =SUMIF(日次入力!$I$5:$I$404,$A11,日次入力!$D$5:$D$404) | D11: =IFERROR($B11/$C11,"") | E11: =IFERROR($B11/$B10-1,"") | H11: =IFERROR($B11/$G11,"")
A12: =TEXT(EDATE($B$4,5),"yyyy/mm") | B12: =SUMIF(日次入力!$I$5:$I$404,$A12,日次入力!$C$5:$C$404) | C12: =SUMIF(日次入力!$I$5:$I$404,$A12,日次入力!$D$5:$D$404) | D12: =IFERROR($B12/$C12,"") | E12: =IFERROR($B12/$B11-1,"") | H12: =IFERROR($B12/$G12,"")
A13: =TEXT(EDATE($B$4,6),"yyyy/mm") | B13: =SUMIF(日次入力!$I$5:$I$404,$A13,日次入力!$C$5:$C$404) | C13: =SUMIF(日次入力!$I$5:$I$404,$A13,日次入力!$D$5:$D$404) | D13: =IFERROR($B13/$C13,"") | E13: =IFERROR($B13/$B12-1,"") | H13: =IFERROR($B13/$G13,"")
A14: =TEXT(EDATE($B$4,7),"yyyy/mm") | B14: =SUMIF(日次入力!$I$5:$I$404,$A14,日次入力!$C$5:$C$404) | C14: =SUMIF(日次入力!$I$5:$I$404,$A14,日次入力!$D$5:$D$404) | D14: =IFERROR($B14/$C14,"") | E14: =IFERROR($B14/$B13-1,"") | H14: =IFERROR($B14/$G14,"")
A15: =TEXT(EDATE($B$4,8),"yyyy/mm") | B15: =SUMIF(日次入力!$I$5:$I$404,$A15,日次入力!$C$5:$C$404) | C15: =SUMIF(日次入力!$I$5:$I$404,$A15,日次入力!$D$5:$D$404) | D15: =IFERROR($B15/$C15,"") | E15: =IFERROR($B15/$B14-1,"") | H15: =IFERROR($B15/$G15,"")
A16: =TEXT(EDATE($B$4,9),"yyyy/mm") | B16: =SUMIF(日次入力!$I$5:$I$404,$A16,日次入力!$C$5:$C$404) | C16: =SUMIF(日次入力!$I$5:$I$404,$A16,日次入力!$D$5:$D$404) | D16: =IFERROR($B16/$C16,"") | E16: =IFERROR($B16/$B15-1,"") | H16: =IFERROR($B16/$G16,"")
A17: =TEXT(EDATE($B$4,10),"yyyy/mm") | B17: =SUMIF(日次入力!$I$5:$I$404,$A17,日次入力!$C$5:$C$404) | C17: =SUMIF(日次入力!$I$5:$I$404,$A17,日次入力!$D$5:$D$404) | D17: =IFERROR($B17/$C17,"") | E17: =IFERROR($B17/$B16-1,"") | H17: =IFERROR($B17/$G17,"")
A18: =TEXT(EDATE($B$4,11),"yyyy/mm") | B18: =SUMIF(日次入力!$I$5:$I$404,$A18,日次入力!$C$5:$C$404) | C18: =SUMIF(日次入力!$I$5:$I$404,$A18,日次入力!$D$5:$D$404) | D18: =IFERROR($B18/$C18,"") | E18: =IFERROR($B18/$B17-1,"") | H18: =IFERROR($B18/$G18,"")
A19: =TEXT(EDATE($B$4,12),"yyyy/mm") | B19: =SUMIF(日次入力!$I$5:$I$404,$A19,日次入力!$C$5:$C$404) | C19: =SUMIF(日次入力!$I$5:$I$404,$A19,日次入力!$D$5:$D$404) | D19: =IFERROR($B19/$C19,"") | E19: =IFERROR($B19/$B18-1,"") | F19: =IFERROR($B19/$B7-1,"") | H19: =IFERROR($B19/$G19,"")
A20: =TEXT(EDATE($B$4,13),"yyyy/mm") | B20: =SUMIF(日次入力!$I$5:$I$404,$A20,日次入力!$C$5:$C$404) | C20: =SUMIF(日次入力!$I$5:$I$404,$A20,日次入力!$D$5:$D$404) | D20: =IFERROR($B20/$C20,"") | E20: =IFERROR($B20/$B19-1,"") | F20: =IFERROR($B20/$B8-1,"") | H20: =IFERROR($B20/$G20,"")
A21: =TEXT(EDATE($B$4,14),"yyyy/mm") | B21: =SUMIF(日次入力!$I$5:$I$404,$A21,日次入力!$C$5:$C$404) | C21: =SUMIF(日次入力!$I$5:$I$404,$A21,日次入力!$D$5:$D$404) | D21: =IFERROR($B21/$C21,"") | E21: =IFERROR($B21/$B20-1,"") | F21: =IFERROR($B21/$B9-1,"") | H21: =IFERROR($B21/$G21,"")
A22: =TEXT(EDATE($B$4,15),"yyyy/mm") | B22: =SUMIF(日次入力!$I$5:$I$404,$A22,日次入力!$C$5:$C$404) | C22: =SUMIF(日次入力!$I$5:$I$404,$A22,日次入力!$D$5:$D$404) | D22: =IFERROR($B22/$C22,"") | E22: =IFERROR($B22/$B21-1,"") | F22: =IFERROR($B22/$B10-1,"") | H22: =IFERROR($B22/$G22,"")
A23: =TEXT(EDATE($B$4,16),"yyyy/mm") | B23: =SUMIF(日次入力!$I$5:$I$404,$A23,日次入力!$C$5:$C$404) | C23: =SUMIF(日次入力!$I$5:$I$404,$A23,日次入力!$D$5:$D$404) | D23: =IFERROR($B23/$C23,"") | E23: =IFERROR($B23/$B22-1,"") | F23: =IFERROR($B23/$B11-1,"") | H23: =IFERROR($B23/$G23,"")
A24: =TEXT(EDATE($B$4,17),"yyyy/mm") | B24: =SUMIF(日次入力!$I$5:$I$404,$A24,日次入力!$C$5:$C$404) | C24: =SUMIF(日次入力!$I$5:$I$404,$A24,日次入力!$D$5:$D$404) | D24: =IFERROR($B24/$C24,"") | E24: =IFERROR($B24/$B23-1,"") | F24: =IFERROR($B24/$B12-1,"") | H24: =IFERROR($B24/$G24,"")
A25: =TEXT(EDATE($B$4,18),"yyyy/mm") | B25: =SUMIF(日次入力!$I$5:$I$404,$A25,日次入力!$C$5:$C$404) | C25: =SUMIF(日次入力!$I$5:$I$404,$A25,日次入力!$D$5:$D$404) | D25: =IFERROR($B25/$C25,"") | E25: =IFERROR($B25/$B24-1,"") | F25: =IFERROR($B25/$B13-1,"") | H25: =IFERROR($B25/$G25,"")
A26: =TEXT(EDATE($B$4,19),"yyyy/mm") | B26: =SUMIF(日次入力!$I$5:$I$404,$A26,日次入力!$C$5:$C$404) | C26: =SUMIF(日次入力!$I$5:$I$404,$A26,日次入力!$D$5:$D$404) | D26: =IFERROR($B26/$C26,"") | E26: =IFERROR($B26/$B25-1,"") | F26: =IFERROR($B26/$B14-1,"") | H26: =IFERROR($B26/$G26,"")
A27: =TEXT(EDATE($B$4,20),"yyyy/mm") | B27: =SUMIF(日次入力!$I$5:$I$404,$A27,日次入力!$C$5:$C$404) | C27: =SUMIF(日次入力!$I$5:$I$404,$A27,日次入力!$D$5:$D$404) | D27: =IFERROR($B27/$C27,"") | E27: =IFERROR($B27/$B26-1,"") | F27: =IFERROR($B27/$B15-1,"") | H27: =IFERROR($B27/$G27,"")
A28: =TEXT(EDATE($B$4,21),"yyyy/mm") | B28: =SUMIF(日次入力!$I$5:$I$404,$A28,日次入力!$C$5:$C$404) | C28: =SUMIF(日次入力!$I$5:$I$404,$A28,日次入力!$D$5:$D$404) | D28: =IFERROR($B28/$C28,"") | E28: =IFERROR($B28/$B27-1,"") | F28: =IFERROR($B28/$B16-1,"") | H28: =IFERROR($B28/$G28,"")
A29: =TEXT(EDATE($B$4,22),"yyyy/mm") | B29: =SUMIF(日次入力!$I$5:$I$404,$A29,日次入力!$C$5:$C$404) | C29: =SUMIF(日次入力!$I$5:$I$404,$A29,日次入力!$D$5:$D$404) | D29: =IFERROR($B29/$C29,"") | E29: =IFERROR($B29/$B28-1,"") | F29: =IFERROR($B29/$B17-1,"") | H29: =IFERROR($B29/$G29,"")
A30: =TEXT(EDATE($B$4,23),"yyyy/mm") | B30: =SUMIF(日次入力!$I$5:$I$404,$A30,日次入力!$C$5:$C$404) | C30: =SUMIF(日次入力!$I$5:$I$404,$A30,日次入力!$D$5:$D$404) | D30: =IFERROR($B30/$C30,"") | E30: =IFERROR($B30/$B29-1,"") | F30: =IFERROR($B30/$B18-1,"") | H30: =IFERROR($B30/$G30,"")
A32: ※ 客単価平均は 売上合計 ÷ 来客数合計。日ごとの客単価を足して割った値とは少しずれます。
A33: ※ 前年同月比は13か月目から出ます。それまでは空欄のままで正常です。
A34: ※ 目標を空のままにすると、達成率も空欄になります。

Sheet グラフ
A1: 売上管理表｜グラフ
A2: 月次集計シートの数字がそのまま出ます。触るところはありません。

Sheet 商品・サービス別
A1: 売上管理表｜商品・サービス別
A2: 青い字のセルに入力してください。粗利と粗利率は自動で出ます。5行目は記入例です。
A4: 商品・サービス名 | B4: 売価 | C4: 原価 | D4: 粗利 | E4: 粗利率 | F4: 月の販売数 | G4: 売上 | H4: 粗利合計
A5: 看板の定食 | B5: 1200 | C5: 540 | D5: =IF($B5="","",$B5-$C5) | E5: =IFERROR($D5/$B5,"") | F5: 320 | G5: =IF($B5="","",$B5*$F5) | H5: =IF($B5="","",$D5*$F5)
D6: =IF($B6="","",$B6-$C6) | E6: =IFERROR($D6/$B6,"") | G6: =IF($B6="","",$B6*$F6) | H6: =IF($B6="","",$D6*$F6)
D7: =IF($B7="","",$B7-$C7) | E7: =IFERROR($D7/$B7,"") | G7: =IF($B7="","",$B7*$F7) | H7: =IF($B7="","",$D7*$F7)
D8: =IF($B8="","",$B8-$C8) | E8: =IFERROR($D8/$B8,"") | G8: =IF($B8="","",$B8*$F8) | H8: =IF($B8="","",$D8*$F8)
D9: =IF($B9="","",$B9-$C9) | E9: =IFERROR($D9/$B9,"") | G9: =IF($B9="","",$B9*$F9) | H9: =IF($B9="","",$D9*$F9)
D10: =IF($B10="","",$B10-$C10) | E10: =IFERROR($D10/$B10,"") | G10: =IF($B10="","",$B10*$F10) | H10: =IF($B10="","",$D10*$F10)
D11: =IF($B11="","",$B11-$C11) | E11: =IFERROR($D11/$B11,"") | G11: =IF($B11="","",$B11*$F11) | H11: =IF($B11="","",$D11*$F11)
D12: =IF($B12="","",$B12-$C12) | E12: =IFERROR($D12/$B12,"") | G12: =IF($B12="","",$B12*$F12) | H12: =IF($B12="","",$D12*$F12)
D13: =IF($B13="","",$B13-$C13) | E13: =IFERROR($D13/$B13,"") | G13: =IF($B13="","",$B13*$F13) | H13: =IF($B13="","",$D13*$F13)
D14: =IF($B14="","",$B14-$C14) | E14: =IFERROR($D14/$B14,"") | G14: =IF($B14="","",$B14*$F14) | H14: =IF($B14="","",$D14*$F14)
D15: =IF($B15="","",$B15-$C15) | E15: =IFERROR($D15/$B15,"") | G15: =IF($B15="","",$B15*$F15) | H15: =IF($B15="","",$D15*$F15)
D16: =IF($B16="","",$B16-$C16) | E16: =IFERROR($D16/$B16,"") | G16: =IF($B16="","",$B16*$F16) | H16: =IF($B16="","",$D16*$F16)
D17: =IF($B17="","",$B17-$C17) | E17: =IFERROR($D17/$B17,"") | G17: =IF($B17="","",$B17*$F17) | H17: =IF($B17="","",$D17*$F17)
... D24: =IF($B24="","",$B24-$C24) | E24: =IFERROR($D24/$B24,"") | G24: =IF($B24="","",$B24*$F24) | H24: =IF($B24="","",$D24*$F24)
A25: 合計 | E25: =IFERROR(H25/G25,"") | G25: =SUM(G5:G24) | H25: =SUM(H5:H24)
A27: ※ 売上が多い商品と、粗利率が高い商品は一致しません。両方を見て売るものを決めてください。
A28: ※ 記入例は 売価1,200円・原価540円（粗利率55%）・月320食。上書きして使ってください。
